[{"chapter":"15","verse":"0","text":"Песнь Давида.","translation_id":"RST","book_id":"Ps","book_name":"Psalms"},{"chapter":"15","verse":"1","text":"Храни меня, Боже, ибо я на Тебя уповаю.","translation_id":"RST","book_id":"Ps","book_name":"Psalms"},{"chapter":"15","verse":"2","text":"Я сказал Господу: Ты Господь мой; блага мои Тебе не нужны.","translation_id":"RST","book_id":"Ps","book_name":"Psalms"},{"chapter":"15","verse":"3","text":"К святым, которые на земле, и к дивным [Твоим] к ним все желание мое.","translation_id":"RST","book_id":"Ps","book_name":"Psalms"},{"chapter":"15","verse":"4","text":"Пусть умножаются скорби у тех, которые текут к [богу] чужому; я не возлию кровавых возлияний их и не помяну имен их устами моими.","translation_id":"RST","book_id":"Ps","book_name":"Psalms"},{"chapter":"15","verse":"5","text":"Господь есть часть наследия моего и чаши моей. Ты держишь жребий мой.","translation_id":"RST","book_id":"Ps","book_name":"Psalms"},{"chapter":"15","verse":"6","text":"Межи мои прошли по прекрасным [местам], и наследие мое приятно для меня.","translation_id":"RST","book_id":"Ps","book_name":"Psalms"},{"chapter":"15","verse":"7","text":"Благословлю Господа, вразумившего меня; даже и ночью учит меня внутренность моя.","translation_id":"RST","book_id":"Ps","book_name":"Psalms"},{"chapter":"15","verse":"8","text":"Всегда видел я пред собою Господа, ибо Он одесную меня; не поколеблюсь.","translation_id":"RST","book_id":"Ps","book_name":"Psalms"},{"chapter":"15","verse":"9","text":"Оттого возрадовалось сердце мое и возвеселился язык мой; даже и плоть моя успокоится в уповании,","translation_id":"RST","book_id":"Ps","book_name":"Psalms"},{"chapter":"15","verse":"10","text":"ибо Ты не оставишь души моей в аде и не дашь святому Твоему увидеть тление,","translation_id":"RST","book_id":"Ps","book_name":"Psalms"},{"chapter":"15","verse":"11","text":"Ты укажешь мне путь жизни: полнота радостей пред лицом Твоим, блаженство в деснице Твоей вовек.","translation_id":"RST","book_id":"Ps","book_name":"Psalms"}]