[{"chapter":2,"verse":1,"text":"Итак прежде всего прошу совершать молитвы, прошения, моления, благодарения за всех человеков,","translation_id":"RST","book_id":"1Tim","book_name":"1 Timothy"},{"chapter":2,"verse":2,"text":"за царей и за всех начальствующих, дабы проводить нам жизнь тихую и безмятежную во всяком благочестии и чистоте,","translation_id":"RST","book_id":"1Tim","book_name":"1 Timothy"},{"chapter":2,"verse":3,"text":"ибо это хорошо и угодно Спасителю нашему Богу,","translation_id":"RST","book_id":"1Tim","book_name":"1 Timothy"},{"chapter":2,"verse":4,"text":"Который хочет, чтобы все люди спаслись и достигли познания истины.","translation_id":"RST","book_id":"1Tim","book_name":"1 Timothy"},{"chapter":2,"verse":5,"text":"Ибо един Бог, един и посредник между Богом и человеками, человек Христос Иисус,","translation_id":"RST","book_id":"1Tim","book_name":"1 Timothy"},{"chapter":2,"verse":6,"text":"предавший Себя для искупления всех. Таково было в свое время свидетельство,","translation_id":"RST","book_id":"1Tim","book_name":"1 Timothy"},{"chapter":2,"verse":7,"text":"для которого я поставлен проповедником и апостолом, – истину говорю во Христе, не лгу, – учителем язычников в вере и истине.","translation_id":"RST","book_id":"1Tim","book_name":"1 Timothy"},{"chapter":2,"verse":8,"text":"Итак желаю, чтобы на всяком месте произносили молитвы мужи, воздевая чистые руки без гнева и сомнения;","translation_id":"RST","book_id":"1Tim","book_name":"1 Timothy"},{"chapter":2,"verse":9,"text":"чтобы также и жены, в приличном одеянии, со стыдливостью и целомудрием, украшали себя не плетением волос, не золотом, не жемчугом, не многоценною одеждою,","translation_id":"RST","book_id":"1Tim","book_name":"1 Timothy"},{"chapter":2,"verse":10,"text":"но добрыми делами, как прилично женам, посвящающим себя благочестию.","translation_id":"RST","book_id":"1Tim","book_name":"1 Timothy"},{"chapter":2,"verse":11,"text":"Жена да учится в безмолвии, со всякою покорностью;","translation_id":"RST","book_id":"1Tim","book_name":"1 Timothy"},{"chapter":2,"verse":12,"text":"а учить жене не позволяю, ни властвовать над мужем, но быть в безмолвии.","translation_id":"RST","book_id":"1Tim","book_name":"1 Timothy"},{"chapter":2,"verse":13,"text":"Ибо прежде создан Адам, а потом Ева;","translation_id":"RST","book_id":"1Tim","book_name":"1 Timothy"},{"chapter":2,"verse":14,"text":"и не Адам прельщен; но жена, прельстившись, впала в преступление;","translation_id":"RST","book_id":"1Tim","book_name":"1 Timothy"},{"chapter":2,"verse":15,"text":"впрочем спасется через чадородие, если пребудет в вере и любви и в святости с целомудрием. ","translation_id":"RST","book_id":"1Tim","book_name":"1 Timothy"}]